setup.py
cary_fortunecommand/__init__.py
cary_fortunecommand.egg-info/PKG-INFO
cary_fortunecommand.egg-info/SOURCES.txt
cary_fortunecommand.egg-info/dependency_links.txt
cary_fortunecommand.egg-info/requires.txt
cary_fortunecommand.egg-info/top_level.txt