Metadata-Version: 1.1
Name: cary-fortunecommand
Version: 1.0.1
Summary: cary command for the unix cowsay and fortune commands
Home-page: https://github.com/vputz/cary
Author: Victor Putz
Author-email: vputz@nyx.net
License: MIT
Keywords: email
Platform: UNKNOWN
Classifier: Development Status :: 4 - Beta
Classifier: Intended Audience :: Developers
Classifier: Topic :: Communications :: Email
Classifier: License :: OSI Approved :: MIT License
Classifier: Programming Language :: Python :: 3
